{
    "cmake_version": "3.8",
    "proj": "test",
    "build": {
        "type": "release",
        "cpp_standard": "11"
    },
    "include_headers": [
        ".",
        "./dir2",
        "dir3"
    ],
    "source_code": {
        "code1": ".",
        "code2": "./code2_path",
        "code3": "code3_path"
    },
    "link": {
        "dir": [
            ".",
            "./paht2",
            "paht3"
        ],
        "lib": [
            "lib1",
            "lib2"
        ]
    },
    "output": {
        "type": "static_lib",
        "name": "test",
        "dir": "./bin"
    }
}